<?xml version="1.0" encoding="utf-8"?>
<FeaturePointList>
    <hand>
        <FeaturePointRadius r="100" />
        <FeaturePoint x="518" y="352" />
        <FeaturePoint x="558" y="270" />
        <FeaturePoint x="486" y="244" />
        <FeaturePoint x="412" y="230" />
        <FeaturePoint x="334" y="232" />
        <FeaturePoint x="288" y="250" />
        <FeaturePoint x="270" y="278" />
        <FeaturePoint x="252" y="350" />
        <FeaturePoint x="246" y="426" />
        <FeaturePoint x="250" y="522" />
        <FeaturePoint x="324" y="632" />
        <FeaturePoint x="354" y="630" />
        <FeaturePoint x="400" y="644" />
        <FeaturePoint x="502" y="606" />
        <FeaturePoint x="568" y="598" />
        <FeaturePoint x="636" y="574" />
        <FeaturePoint x="642" y="518" />
        <FeaturePoint x="666" y="424" />
        <FeaturePoint x="632" y="376" />
        <FeaturePoint x="596" y="282" />
        <FeaturePoint x="562" y="282" />
        <FeaturePoint x="506" y="232" />
    </hand>
</FeaturePointList>