<?xml version="1.0" encoding="utf-8"?>
<FeaturePointList>
    <hand>
        <FeaturePointRadius r="100" />
        <FeaturePoint x="382" y="614" />
        <FeaturePoint x="232" y="718" />
        <FeaturePoint x="480" y="516" />
        <FeaturePoint x="192" y="780" />
        <FeaturePoint x="532" y="464" />
        <FeaturePoint x="128" y="862" />
        <FeaturePoint x="616" y="376" />
        <FeaturePoint x="60" y="946" />
        <FeaturePoint x="668" y="346" />
        <FeaturePoint x="296" y="664" />
    </hand>
</FeaturePointList>