<?xml version="1.0" encoding="utf-8"?>
<FeaturePointList>
    <hand>
        <FeaturePointRadius r="100" />
        <FeaturePoint x="482" y="398" />
        <FeaturePoint x="476" y="508" />
        <FeaturePoint x="472" y="614" />
        <FeaturePoint x="464" y="692" />
        <FeaturePoint x="458" y="750" />
        <FeaturePoint x="460" y="696" />
        <FeaturePoint x="336" y="690" />
        <FeaturePoint x="242" y="672" />
        <FeaturePoint x="340" y="692" />
        <FeaturePoint x="464" y="698" />
        <FeaturePoint x="472" y="620" />
        <FeaturePoint x="592" y="554" />
        <FeaturePoint x="610" y="398" />
    </hand>
</FeaturePointList>